{"type":"FeatureCollection","crs":{"type":"name","properties":{"name":"EPSG:32640"}},"features":[{"type":"Feature","id":3,"geometry":{"type":"Point","coordinates":[186290.68850000016,1882719.8922000006]},"properties":{"OBJECTID":3,"Asset_ID":"C3","Name":"Oman College of Health Sciences","District_ID":"13","Gov_ID":"2","Wlyt_ID":"Salalah","Road_ID":null,"Latitude":17.00726968,"Longitude":54.053772199999997,"GlobalID":"{1163C0E8-F499-4949-A284-165DCDEDFEBB}","NEAR_FID":null,"NEAR_DIST":null}}]}