{"type":"FeatureCollection","crs":{"type":"name","properties":{"name":"EPSG:32640"}},"features":[{"type":"Feature","id":1,"geometry":{"type":"Point","coordinates":[197478.7723000003,1887486.7539000008]},"properties":{"OBJECTID":1,"Asset_ID":"HC1","Name":"Alsaada Health Centre","District_ID":"al Sada al Janubiyya","Gov_ID":"2","Wlyt_ID":"Salalah","Road_ID":"100324","Latitude":17.0518,"Longitude":54.158099999999997,"GlobalID":"{93756538-6FE7-4ECF-945E-72C91EE4E069}","NEAR_FID":4765,"NEAR_DIST":91.270378290499323}},{"type":"Feature","id":2,"geometry":{"type":"Point","coordinates":[190190.72649999987,1883904.7890000008]},"properties":{"OBJECTID":2,"Asset_ID":"HC2","Name":"Salalah Al Jadidah Health Center","District_ID":"Salalah al Jadida","Gov_ID":"2","Wlyt_ID":"Salalah","Road_ID":"104200","Latitude":17.01849344,"Longitude":54.090199820000002,"GlobalID":"{901E7C99-CC34-4F9C-B485-5F5112FEF9A7}","NEAR_FID":15283,"NEAR_DIST":49.533369859616926}},{"type":"Feature","id":3,"geometry":{"type":"Point","coordinates":[188812.86110000033,1882939.0494999997]},"properties":{"OBJECTID":3,"Asset_ID":"HC3","Name":"Salalah Al Gharbia Health center","District_ID":"Salalah al Gharbiyya","Gov_ID":"2","Wlyt_ID":"Salalah","Road_ID":null,"Latitude":17.009589559999998,"Longitude":54.077406189999998,"GlobalID":"{63809FE2-E0A6-4DDF-8919-948B9DF1EE94}","NEAR_FID":null,"NEAR_DIST":null}},{"type":"Feature","id":4,"geometry":{"type":"Point","coordinates":[199046.4589999998,1884282.7580999993]},"properties":{"OBJECTID":4,"Asset_ID":"HC4","Name":"Dahariz Health Center","District_ID":"Dahariz al Shamaliyya","Gov_ID":"2","Wlyt_ID":"Salalah","Road_ID":null,"Latitude":17.02307837,"Longitude":54.173248909999998,"GlobalID":"{7D2B3292-6909-4DF8-B0A7-2E7AE54D72F8}","NEAR_FID":null,"NEAR_DIST":null}}]}