{"type":"FeatureCollection","crs":{"type":"name","properties":{"name":"EPSG:32640"}},"features":[{"type":"Feature","id":1,"geometry":{"type":"Point","coordinates":[198195.61959999986,1884224.7530000005]},"properties":{"OBJECTID":1,"Asset_ID":"VP1","Name":"Dr Abotaha Vet","District_ID":"Dahariz al Shamaliyya","Gov_ID":"2","Wlyt_ID":"Salalah","Road_ID":"100002","Latitude":17.02244348,"Longitude":54.165272270000003,"GlobalID":"{64001085-B63D-4037-9EE1-7BEF8CD7A90A}","NEAR_FID":18925,"NEAR_DIST":21.089958810209861}},{"type":"Feature","id":2,"geometry":{"type":"Point","coordinates":[196789.13370000012,1892762.307]},"properties":{"OBJECTID":2,"Asset_ID":"VP2","Name":"صيدلية بيطرية","District_ID":null,"Gov_ID":"2","Wlyt_ID":"Salalah","Road_ID":"102011","Latitude":17.099338270000001,"Longitude":54.150903749999998,"GlobalID":"{F6ACBE35-DE91-4CA8-84D0-AEAE48596EFA}","NEAR_FID":285,"NEAR_DIST":39.816466060680554}},{"type":"Feature","id":3,"geometry":{"type":"Point","coordinates":[196327.68329999968,1892668.5875000004]},"properties":{"OBJECTID":3,"Asset_ID":"VP3","Name":"صيدلية الشام البيطرية","District_ID":null,"Gov_ID":"2","Wlyt_ID":"Salalah","Road_ID":"102167","Latitude":17.098431139999999,"Longitude":54.146584570000002,"GlobalID":"{374D6FDE-7AD6-4E40-9F01-F2F7A2C63D7B}","NEAR_FID":7830,"NEAR_DIST":32.024813866043708}},{"type":"Feature","id":4,"geometry":{"type":"Point","coordinates":[187840.42040000018,1882488.9005999994]},"properties":{"OBJECTID":4,"Asset_ID":"VP4","Name":"العيادة البيطرية","District_ID":"Salalah al Gharbiyya","Gov_ID":"2","Wlyt_ID":"Salalah","Road_ID":null,"Latitude":null,"Longitude":null,"GlobalID":"{88E8991D-5A06-4624-9694-A1A4FCA118B2}","NEAR_FID":null,"NEAR_DIST":null}}]}